{"month":5,"count":21,"run_count":21,"distance_mi":139.76,"run_distance_mi":139.76,"elevation_m":3385.8,"weeks":[{"week":"2015-W18","count":1,"run_count":1,"distance_mi":8.76,"run_distance_mi":8.76,"elevation_m":1220.8,"activities":[{"id":"297711816","name":"Mt Baldy Loop","type":"Run","date":"2015-05-01T14:53:06","description":"And yes, I took the chairlift down, as you can see from the straight line. Fantastic place, but the 10,000' altitude took it out of me nicely!","distance_mi":8.76,"moving_time_s":12572,"elevation_m":1220.8,"avg_hr":130,"max_hr":155,"avg_cadence":null,"calories":1980,"with_pet":null,"with_kid":null}]},{"week":"2015-W19","count":4,"run_count":4,"distance_mi":32.51,"run_distance_mi":32.51,"elevation_m":790.7,"activities":[{"id":"298391441","name":"Long Medina Loop","type":"Run","date":"2015-05-05T00:43:47","description":"Lots of stops unfortunately!","distance_mi":7.59,"moving_time_s":3875,"elevation_m":169.5,"avg_hr":null,"max_hr":null,"avg_cadence":null,"calories":null,"with_pet":null,"with_kid":null},{"id":"299270301","name":"Wet and Wandering","type":"Run","date":"2015-05-06T01:04:31","description":"Nice downpour as I explored some of the quieter streets of Medina near my usual route.","distance_mi":4.98,"moving_time_s":2514,"elevation_m":86.3,"avg_hr":null,"max_hr":null,"avg_cadence":null,"calories":null,"with_pet":null,"with_kid":null},{"id":"300579480","name":"treadmill","type":"Run","date":"2015-05-08T01:00:00","description":"400-500 feet of climbing","distance_mi":4.0,"moving_time_s":2120,"elevation_m":null,"avg_hr":null,"max_hr":null,"avg_cadence":null,"calories":628,"with_pet":null,"with_kid":null},{"id":"301323152","name":"Too hot to run 20 miles","type":"Run","date":"2015-05-09T15:59:13","description":"Somehow Herve managed it, but I'm not as tough as he is!","distance_mi":15.94,"moving_time_s":8802,"elevation_m":534.9,"avg_hr":null,"max_hr":null,"avg_cadence":null,"calories":2720,"with_pet":null,"with_kid":null}]},{"week":"2015-W20","count":7,"run_count":7,"distance_mi":34.65,"run_distance_mi":34.65,"elevation_m":455.6,"activities":[{"id":"304010705","name":"Treadmill + erg","type":"Run","date":"2015-05-12T01:00:00","description":"Feeling a little light-headed","distance_mi":3.5,"moving_time_s":1800,"elevation_m":null,"avg_hr":null,"max_hr":null,"avg_cadence":null,"calories":549,"with_pet":null,"with_kid":null},{"id":"304643495","name":"Medina Loop sans watch","type":"Run","date":"2015-05-14T00:30:00","description":null,"distance_mi":4.8,"moving_time_s":2760,"elevation_m":null,"avg_hr":null,"max_hr":null,"avg_cadence":null,"calories":753,"with_pet":null,"with_kid":null},{"id":"306525945","name":"Short Medina Loop (walking)","type":"Run","date":"2015-05-15T00:34:30","description":null,"distance_mi":4.28,"moving_time_s":2736,"elevation_m":72.7,"avg_hr":null,"max_hr":null,"avg_cadence":null,"calories":682,"with_pet":null,"with_kid":null},{"id":"306523246","name":"First day at Studio A.","type":"Run","date":"2015-05-16T00:02:38","description":"Low blood sugar after 2 miles.","distance_mi":2.3,"moving_time_s":1127,"elevation_m":null,"avg_hr":null,"max_hr":null,"avg_cadence":null,"calories":null,"with_pet":null,"with_kid":null},{"id":"306523281","name":"Walk/Jog back to office","type":"Run","date":"2015-05-16T00:26:45","description":null,"distance_mi":2.5,"moving_time_s":1833,"elevation_m":115.0,"avg_hr":null,"max_hr":null,"avg_cadence":null,"calories":null,"with_pet":null,"with_kid":null},{"id":"306523302","name":"Phinney Fremont","type":"Run","date":"2015-05-16T15:09:56","description":"Lots of walking. Still feeling crappy.","distance_mi":4.82,"moving_time_s":2703,"elevation_m":129.9,"avg_hr":null,"max_hr":null,"avg_cadence":null,"calories":null,"with_pet":null,"with_kid":null},{"id":"306523339","name":"Both Lakes","type":"Run","date":"2015-05-17T15:21:59","description":"Felt better than I expected!","distance_mi":12.45,"moving_time_s":6815,"elevation_m":138.0,"avg_hr":null,"max_hr":null,"avg_cadence":null,"calories":null,"with_pet":null,"with_kid":null}]},{"week":"2015-W21","count":3,"run_count":3,"distance_mi":17.61,"run_distance_mi":17.61,"elevation_m":171.9,"activities":[{"id":"308278129","name":"Run Home-ish","type":"Run","date":"2015-05-20T00:22:38","description":"Bus across the bridge, and bonked for lack of energy a mile or two from home, but this is definitely a fun way to end the day!","distance_mi":8.03,"moving_time_s":4387,"elevation_m":114.5,"avg_hr":null,"max_hr":null,"avg_cadence":null,"calories":null,"with_pet":null,"with_kid":null},{"id":"310390553","name":"05/22/2015 Seattle, WA","type":"Run","date":"2015-05-22T13:48:41","description":null,"distance_mi":4.04,"moving_time_s":2051,"elevation_m":31.7,"avg_hr":null,"max_hr":null,"avg_cadence":null,"calories":null,"with_pet":null,"with_kid":null},{"id":"310390551","name":"To Mathews beach and back with Mino and Grace","type":"Run","date":"2015-05-23T17:55:52","description":"Really fun to have Grace get into running. She ran home after this!","distance_mi":5.54,"moving_time_s":2822,"elevation_m":25.7,"avg_hr":null,"max_hr":null,"avg_cadence":null,"calories":875,"with_pet":null,"with_kid":null}]},{"week":"2015-W22","count":6,"run_count":6,"distance_mi":46.23,"run_distance_mi":46.23,"elevation_m":746.8,"activities":[{"id":"312229797","name":"Cut down guitar run","type":"Run","date":"2015-05-25T17:06:03","description":"ran out of energy.... lots of stops","distance_mi":8.64,"moving_time_s":4641,"elevation_m":133.0,"avg_hr":null,"max_hr":null,"avg_cadence":null,"calories":null,"with_pet":null,"with_kid":null},{"id":"313852975","name":"Early morning electric guitar run","type":"Run","date":"2015-05-28T12:51:46","description":"Not too bad.","distance_mi":10.02,"moving_time_s":5313,"elevation_m":141.4,"avg_hr":null,"max_hr":null,"avg_cadence":null,"calories":1595,"with_pet":null,"with_kid":null},{"id":"314149588","name":"Green Lake 5K","type":"Run","date":"2015-05-29T13:57:39","description":null,"distance_mi":3.13,"moving_time_s":1559,"elevation_m":null,"avg_hr":null,"max_hr":null,"avg_cadence":null,"calories":492,"with_pet":null,"with_kid":null},{"id":"315888924","name":"Interlaken to the Arboretum","type":"Run","date":"2015-05-30T14:39:25","description":null,"distance_mi":2.15,"moving_time_s":1135,"elevation_m":47.7,"avg_hr":null,"max_hr":null,"avg_cadence":null,"calories":351,"with_pet":null,"with_kid":null},{"id":"315888929","name":"Walk, then run, back up Interlaken","type":"Run","date":"2015-05-30T15:05:33","description":null,"distance_mi":2.24,"moving_time_s":1696,"elevation_m":50.3,"avg_hr":null,"max_hr":null,"avg_cadence":null,"calories":364,"with_pet":null,"with_kid":null},{"id":"315888955","name":"Out and back on the Snoq Valley / Iron Horse","type":"Run","date":"2015-05-31T14:25:35","description":"Did it by myself, and felt pretty good until about the 18 mile mark. Then -- not so good.","distance_mi":20.05,"moving_time_s":11184,"elevation_m":374.4,"avg_hr":null,"max_hr":null,"avg_cadence":null,"calories":3222,"with_pet":null,"with_kid":null}]}]}