{"month":11,"count":26,"run_count":24,"distance_mi":118.57,"run_distance_mi":112.83,"elevation_m":2534.6,"weeks":[{"week":"2020-W44","count":1,"run_count":0,"distance_mi":2.89,"run_distance_mi":0,"elevation_m":12.0,"activities":[{"id":"4273138763","name":"Trees of Green Lake","type":"Hike","date":"2020-11-01T17:57:29","description":"Chris and I actually walked around Green Lake together!","distance_mi":2.89,"moving_time_s":3642,"elevation_m":12.0,"avg_hr":null,"max_hr":null,"avg_cadence":58,"calories":278,"with_pet":null,"with_kid":null}]},{"week":"2020-W45","count":6,"run_count":6,"distance_mi":22.05,"run_distance_mi":22.05,"elevation_m":442.2,"activities":[{"id":"4274068338","name":"Easy Wallingford","type":"Run","date":"2020-11-02T00:07:37","description":null,"distance_mi":2.31,"moving_time_s":1322,"elevation_m":53.2,"avg_hr":null,"max_hr":null,"avg_cadence":81,"calories":313,"with_pet":null,"with_kid":null},{"id":"4278435473","name":"Do flu shots help your running?","type":"Run","date":"2020-11-03T00:23:58","description":"Mine seemed to today!","distance_mi":3.69,"moving_time_s":1975,"elevation_m":61.0,"avg_hr":null,"max_hr":null,"avg_cadence":83,"calories":487,"with_pet":null,"with_kid":null},{"id":"4282847538","name":"Short run before the election results","type":"Run","date":"2020-11-03T23:15:29","description":null,"distance_mi":2.07,"moving_time_s":1083,"elevation_m":43.0,"avg_hr":null,"max_hr":null,"avg_cadence":83,"calories":272,"with_pet":null,"with_kid":null},{"id":"4292273921","name":"Bonk happens","type":"Run","date":"2020-11-06T00:14:50","description":"Did 2 of 5 miles nicely then fell off a cliff. I\u2019ll take it.","distance_mi":2.83,"moving_time_s":1724,"elevation_m":55.0,"avg_hr":null,"max_hr":null,"avg_cadence":76,"calories":368,"with_pet":null,"with_kid":null},{"id":"4298648631","name":"Hooray! \u201cDown Dayton\u201d loop under 9","type":"Run","date":"2020-11-06T19:51:13","description":"In blustery conditions no less.","distance_mi":4.29,"moving_time_s":2283,"elevation_m":73.0,"avg_hr":null,"max_hr":null,"avg_cadence":82,"calories":576,"with_pet":null,"with_kid":null},{"id":"4303884913","name":"President Biden!","type":"Run","date":"2020-11-07T17:13:54","description":"With Anita and Mintu","distance_mi":6.86,"moving_time_s":4157,"elevation_m":157.0,"avg_hr":null,"max_hr":null,"avg_cadence":81,"calories":918,"with_pet":null,"with_kid":null}]},{"week":"2020-W46","count":6,"run_count":6,"distance_mi":28.08,"run_distance_mi":28.08,"elevation_m":389.0,"activities":[{"id":"4313357027","name":"Runs better when cold","type":"Run","date":"2020-11-09T15:57:37","description":"Mid 30s are my perfect running temps","distance_mi":4.65,"moving_time_s":2503,"elevation_m":84.0,"avg_hr":null,"max_hr":null,"avg_cadence":82,"calories":629,"with_pet":null,"with_kid":null},{"id":"4319339415","name":"Trying not to push it","type":"Run","date":"2020-11-10T20:08:02","description":"... and I go almost the same speed as when I am pushing it. There\u2019s a lesson here.","distance_mi":3.85,"moving_time_s":2094,"elevation_m":84.0,"avg_hr":null,"max_hr":null,"avg_cadence":82,"calories":521,"with_pet":null,"with_kid":null},{"id":"4324270862","name":"Pushed fairly hard","type":"Run","date":"2020-11-11T19:38:05","description":"And made up a minute. 3rd good run in 3 days. I\u2019m a happy chap.","distance_mi":3.84,"moving_time_s":2027,"elevation_m":78.0,"avg_hr":null,"max_hr":null,"avg_cadence":82,"calories":516,"with_pet":null,"with_kid":null},{"id":"4333089027","name":"Suddenly sunny","type":"Run","date":"2020-11-13T19:54:14","description":"Dressed too warmly; had a number of my \u201csun stops\u201d","distance_mi":2.73,"moving_time_s":1464,"elevation_m":61.0,"avg_hr":null,"max_hr":null,"avg_cadence":82,"calories":370,"with_pet":null,"with_kid":null},{"id":"4338102965","name":"Back to the Cedar River Trail","type":"Run","date":"2020-11-14T17:27:41","description":"Out and back with  M & A","distance_mi":11.19,"moving_time_s":6001,"elevation_m":63.0,"avg_hr":null,"max_hr":null,"avg_cadence":83,"calories":1460,"with_pet":null,"with_kid":null},{"id":"4343303020","name":"Little recovery after yesterday\u2019s exertions","type":"Run","date":"2020-11-15T17:53:07","description":"Felt as ungainly as this path looks.","distance_mi":1.82,"moving_time_s":1033,"elevation_m":19.0,"avg_hr":null,"max_hr":null,"avg_cadence":82,"calories":235,"with_pet":null,"with_kid":null}]},{"week":"2020-W47","count":6,"run_count":6,"distance_mi":25.31,"run_distance_mi":25.31,"elevation_m":600.0,"activities":[{"id":"4352704582","name":"Be-drenched, bedraggled, and bespattered","type":"Run","date":"2020-11-17T20:10:38","description":"Exquisitely bad timing in the downpours. The joys of running in November in Seattle.","distance_mi":3.2,"moving_time_s":1744,"elevation_m":81.0,"avg_hr":null,"max_hr":null,"avg_cadence":82,"calories":431,"with_pet":null,"with_kid":null},{"id":"4358226796","name":"I don\u2019t mind rainy and windy","type":"Run","date":"2020-11-19T00:18:23","description":"But I draw the line at rainy, windy, and dark.","distance_mi":3.64,"moving_time_s":2001,"elevation_m":88.0,"avg_hr":null,"max_hr":null,"avg_cadence":82,"calories":474,"with_pet":null,"with_kid":null},{"id":"4361810640","name":"Smoothly up Dayton","type":"Run","date":"2020-11-19T19:47:01","description":"And achieved my goal of a 9 min pace. Hooray.","distance_mi":4.24,"moving_time_s":2269,"elevation_m":74.0,"avg_hr":null,"max_hr":null,"avg_cadence":82,"calories":562,"with_pet":null,"with_kid":null},{"id":"4366122288","name":"Hair tie around Tangletown","type":"Run","date":"2020-11-20T20:17:21","description":null,"distance_mi":3.01,"moving_time_s":1683,"elevation_m":66.0,"avg_hr":null,"max_hr":null,"avg_cadence":81,"calories":406,"with_pet":null,"with_kid":null},{"id":"4370981642","name":"A spear jabbing Lake City","type":"Run","date":"2020-11-21T17:08:59","description":"One of my favorite run designs. Hard to make long Jordan Curves in that corner of the city, but we did it.","distance_mi":9.01,"moving_time_s":5147,"elevation_m":236.0,"avg_hr":null,"max_hr":null,"avg_cadence":81,"calories":1195,"with_pet":null,"with_kid":null},{"id":"4377217391","name":"Jog/walk on Phinney with Chris","type":"Run","date":"2020-11-22T19:35:04","description":null,"distance_mi":2.21,"moving_time_s":1884,"elevation_m":55.0,"avg_hr":null,"max_hr":null,"avg_cadence":72,"calories":238,"with_pet":null,"with_kid":null}]},{"week":"2020-W48","count":6,"run_count":5,"distance_mi":35.97,"run_distance_mi":33.12,"elevation_m":1023.4,"activities":[{"id":"4382228441","name":"Mud puddles of Bridle Trails","type":"Run","date":"2020-11-24T01:00:00","description":"GPS went wonky after 3 miles... thought I had detoured to south Seattle.","distance_mi":4.19,"moving_time_s":2570,"elevation_m":91.4,"avg_hr":null,"max_hr":null,"avg_cadence":null,"calories":658,"with_pet":null,"with_kid":null},{"id":"4390305150","name":"Rolling Hills of Loyal Heights","type":"Run","date":"2020-11-25T17:21:55","description":"With Mintu and Anita","distance_mi":8.37,"moving_time_s":4633,"elevation_m":101.0,"avg_hr":null,"max_hr":null,"avg_cadence":82,"calories":1113,"with_pet":null,"with_kid":null},{"id":"4394707774","name":"Checking out the old growth of Seward Park","type":"Hike","date":"2020-11-26T17:55:34","description":"With Chris, Tamara and Nick. Giving thanks for old trees and good friends.","distance_mi":2.85,"moving_time_s":4467,"elevation_m":44.0,"avg_hr":null,"max_hr":null,"avg_cadence":56,"calories":287,"with_pet":null,"with_kid":null},{"id":"4399015882","name":"East Tiger Zigzags with Mark and Mintu","type":"Run","date":"2020-11-27T18:07:27","description":null,"distance_mi":10.08,"moving_time_s":7217,"elevation_m":462.0,"avg_hr":null,"max_hr":null,"avg_cadence":78,"calories":1200,"with_pet":null,"with_kid":null},{"id":"4404702963","name":"Easy does it","type":"Run","date":"2020-11-29T00:03:38","description":"Keeping it Jordan in Tangletown.","distance_mi":3.29,"moving_time_s":1908,"elevation_m":66.0,"avg_hr":null,"max_hr":null,"avg_cadence":81,"calories":444,"with_pet":null,"with_kid":null},{"id":"4409873393","name":"Fremont Street Scramble in the Sunshine","type":"Run","date":"2020-11-29T20:29:38","description":"Thank you Peter and Lauren!","distance_mi":7.19,"moving_time_s":4718,"elevation_m":259.0,"avg_hr":null,"max_hr":null,"avg_cadence":78,"calories":916,"with_pet":null,"with_kid":null}]},{"week":"2020-W49","count":1,"run_count":1,"distance_mi":4.27,"run_distance_mi":4.27,"elevation_m":68.0,"activities":[{"id":"4413406134","name":"Solid pace for tired legs","type":"Run","date":"2020-11-30T20:16:00","description":"Almost too warm for long sleeves!","distance_mi":4.27,"moving_time_s":2307,"elevation_m":68.0,"avg_hr":null,"max_hr":null,"avg_cadence":82,"calories":574,"with_pet":null,"with_kid":null}]}]}