{"year":2012,"count":126,"run_count":124,"distance_mi":562.76,"run_distance_mi":545.25,"elevation_m":26930.8,"months":[{"month":1,"count":3,"run_count":3,"distance_mi":12.36,"run_distance_mi":12.36,"elevation_m":890.4,"weeks":[{"week":"2012-W03","count":1,"run_count":1,"distance_mi":4.59,"run_distance_mi":4.59,"elevation_m":737.5,"activities":[{"id":"128152307","name":"01/22/2012 North Bend, WA","type":"Run","date":"2012-01-22T17:12:49","description":null,"distance_mi":4.59,"moving_time_s":6161,"elevation_m":737.5,"avg_hr":140,"max_hr":157,"avg_cadence":null,"calories":1064,"with_pet":null,"with_kid":null}]},{"week":"2012-W04","count":2,"run_count":2,"distance_mi":7.77,"run_distance_mi":7.77,"elevation_m":152.9,"activities":[{"id":"128152297","name":"Tangletown Hilly 4miler","type":"Run","date":"2012-01-28T23:22:50","description":null,"distance_mi":4.0,"moving_time_s":1999,"elevation_m":71.6,"avg_hr":168,"max_hr":182,"avg_cadence":null,"calories":636,"with_pet":null,"with_kid":null},{"id":"128152291","name":"01/29/2012 Seattle, WA","type":"Run","date":"2012-01-29T23:40:15","description":null,"distance_mi":3.77,"moving_time_s":2076,"elevation_m":81.3,"avg_hr":155,"max_hr":174,"avg_cadence":null,"calories":591,"with_pet":null,"with_kid":null}]}]},{"month":2,"count":9,"run_count":9,"distance_mi":36.19,"run_distance_mi":36.19,"elevation_m":1325.0,"weeks":[{"week":"2012-W05","count":2,"run_count":2,"distance_mi":7.68,"run_distance_mi":7.68,"elevation_m":165.5,"activities":[{"id":"128152288","name":"02/04/2012 Seattle, WA","type":"Run","date":"2012-02-04T22:51:48","description":null,"distance_mi":2.73,"moving_time_s":1647,"elevation_m":35.5,"avg_hr":155,"max_hr":173,"avg_cadence":null,"calories":425,"with_pet":null,"with_kid":null},{"id":"128152283","name":"02/05/2012 Seattle, WA","type":"Run","date":"2012-02-05T22:46:33","description":null,"distance_mi":4.95,"moving_time_s":2866,"elevation_m":130.0,"avg_hr":151,"max_hr":180,"avg_cadence":null,"calories":774,"with_pet":null,"with_kid":null}]},{"week":"2012-W06","count":2,"run_count":2,"distance_mi":9.05,"run_distance_mi":9.05,"elevation_m":681.6,"activities":[{"id":"128152269","name":"02/11/2012 Seattle, WA","type":"Run","date":"2012-02-11T23:52:05","description":null,"distance_mi":3.74,"moving_time_s":1946,"elevation_m":71.3,"avg_hr":null,"max_hr":null,"avg_cadence":null,"calories":581,"with_pet":null,"with_kid":null},{"id":"128152277","name":"02/12/2012 Issaquah, WA","type":"Run","date":"2012-02-12T16:22:08","description":null,"distance_mi":5.31,"moving_time_s":4636,"elevation_m":610.3,"avg_hr":null,"max_hr":null,"avg_cadence":null,"calories":1012,"with_pet":null,"with_kid":null}]},{"week":"2012-W07","count":3,"run_count":3,"distance_mi":11.54,"run_distance_mi":11.54,"elevation_m":218.8,"activities":[{"id":"128152266","name":"02/17/2012 Bellevue, WA","type":"Run","date":"2012-02-17T15:30:16","description":null,"distance_mi":4.39,"moving_time_s":2326,"elevation_m":74.2,"avg_hr":155,"max_hr":189,"avg_cadence":null,"calories":677,"with_pet":null,"with_kid":null},{"id":"128152263","name":"02/18/2012 Seattle, WA","type":"Run","date":"2012-02-18T20:35:21","description":null,"distance_mi":3.9,"moving_time_s":2533,"elevation_m":75.1,"avg_hr":136,"max_hr":166,"avg_cadence":null,"calories":623,"with_pet":null,"with_kid":null},{"id":"128152251","name":"02/19/2012 Seattle, WA","type":"Run","date":"2012-02-19T23:10:05","description":null,"distance_mi":3.25,"moving_time_s":1745,"elevation_m":69.5,"avg_hr":154,"max_hr":170,"avg_cadence":null,"calories":502,"with_pet":null,"with_kid":null}]},{"week":"2012-W08","count":2,"run_count":2,"distance_mi":7.92,"run_distance_mi":7.92,"elevation_m":259.1,"activities":[{"id":"128152240","name":"02/25/2012 Seattle, WA","type":"Run","date":"2012-02-25T21:20:33","description":null,"distance_mi":4.02,"moving_time_s":2026,"elevation_m":72.1,"avg_hr":166,"max_hr":183,"avg_cadence":null,"calories":620,"with_pet":null,"with_kid":null},{"id":"128152238","name":"02/26/2012 Newcastle, WA","type":"Run","date":"2012-02-26T19:19:55","description":null,"distance_mi":3.9,"moving_time_s":2655,"elevation_m":187.0,"avg_hr":149,"max_hr":166,"avg_cadence":null,"calories":646,"with_pet":null,"with_kid":null}]}]},{"month":3,"count":6,"run_count":6,"distance_mi":29.45,"run_distance_mi":29.45,"elevation_m":1188.0,"weeks":[{"week":"2012-W09","count":1,"run_count":1,"distance_mi":5.78,"run_distance_mi":5.78,"elevation_m":168.0,"activities":[{"id":"128152237","name":"03/03/2012 Seattle, WA","type":"Run","date":"2012-03-03T19:04:52","description":null,"distance_mi":5.78,"moving_time_s":3359,"elevation_m":168.0,"avg_hr":157,"max_hr":170,"avg_cadence":null,"calories":916,"with_pet":null,"with_kid":null}]},{"week":"2012-W10","count":1,"run_count":1,"distance_mi":5.77,"run_distance_mi":5.77,"elevation_m":166.7,"activities":[{"id":"128152230","name":"03/04/2012 Seattle, WA","type":"Run","date":"2012-03-05T00:22:14","description":null,"distance_mi":5.77,"moving_time_s":3072,"elevation_m":166.7,"avg_hr":163,"max_hr":176,"avg_cadence":null,"calories":912,"with_pet":null,"with_kid":null}]},{"week":"2012-W12","count":2,"run_count":2,"distance_mi":12.96,"run_distance_mi":12.96,"elevation_m":509.2,"activities":[{"id":"128152226","name":"03/24/2012 Newcastle, WA","type":"Run","date":"2012-03-24T21:35:55","description":null,"distance_mi":7.24,"moving_time_s":4773,"elevation_m":332.4,"avg_hr":157,"max_hr":171,"avg_cadence":null,"calories":1202,"with_pet":null,"with_kid":null},{"id":"128152210","name":"03/25/2012 Seattle, WA","type":"Run","date":"2012-03-25T16:14:19","description":null,"distance_mi":5.72,"moving_time_s":3149,"elevation_m":176.8,"avg_hr":163,"max_hr":179,"avg_cadence":null,"calories":904,"with_pet":null,"with_kid":null}]},{"week":"2012-W13","count":2,"run_count":2,"distance_mi":4.94,"run_distance_mi":4.94,"elevation_m":344.1,"activities":[{"id":"128152201","name":"03/31/2012 Seattle, WA","type":"Run","date":"2012-03-31T18:46:10","description":null,"distance_mi":2.14,"moving_time_s":2421,"elevation_m":344.1,"avg_hr":149,"max_hr":176,"avg_cadence":null,"calories":504,"with_pet":null,"with_kid":null},{"id":"128152187","name":"03/31/2012 Seattle, WA","type":"Run","date":"2012-03-31T19:54:20","description":null,"distance_mi":2.8,"moving_time_s":1969,"elevation_m":null,"avg_hr":128,"max_hr":150,"avg_cadence":null,"calories":430,"with_pet":null,"with_kid":null}]}]},{"month":4,"count":16,"run_count":16,"distance_mi":57.81,"run_distance_mi":57.81,"elevation_m":3505.5,"weeks":[{"week":"2012-W13","count":1,"run_count":1,"distance_mi":3.21,"run_distance_mi":3.21,"elevation_m":71.7,"activities":[{"id":"128152176","name":"04/01/2012 Seattle, WA","type":"Run","date":"2012-04-01T16:19:03","description":null,"distance_mi":3.21,"moving_time_s":1729,"elevation_m":71.7,"avg_hr":null,"max_hr":null,"avg_cadence":null,"calories":497,"with_pet":null,"with_kid":null}]},{"week":"2012-W14","count":2,"run_count":2,"distance_mi":13.18,"run_distance_mi":13.18,"elevation_m":991.7,"activities":[{"id":"128152168","name":"04/06/2012 Seattle, WA","type":"Run","date":"2012-04-07T01:01:33","description":null,"distance_mi":3.2,"moving_time_s":1521,"elevation_m":null,"avg_hr":169,"max_hr":179,"avg_cadence":null,"calories":488,"with_pet":null,"with_kid":null},{"id":"128152180","name":"West Tiger Lollipop","type":"Run","date":"2012-04-07T14:52:48","description":null,"distance_mi":9.98,"moving_time_s":8609,"elevation_m":991.7,"avg_hr":148,"max_hr":166,"avg_cadence":null,"calories":1923,"with_pet":null,"with_kid":null}]},{"week":"2012-W15","count":8,"run_count":8,"distance_mi":20.78,"run_distance_mi":20.78,"elevation_m":1199.1,"activities":[{"id":"128152159","name":"04/08/2012 Seattle, WA","type":"Run","date":"2012-04-09T00:27:07","description":null,"distance_mi":2.43,"moving_time_s":1742,"elevation_m":68.0,"avg_hr":138,"max_hr":169,"avg_cadence":null,"calories":null,"with_pet":null,"with_kid":null},{"id":"128152150","name":"04/10/2012 Bellevue, WA","type":"Run","date":"2012-04-10T14:26:10","description":null,"distance_mi":3.73,"moving_time_s":1964,"elevation_m":57.5,"avg_hr":152,"max_hr":167,"avg_cadence":null,"calories":575,"with_pet":null,"with_kid":null},{"id":"128152147","name":"04/13/2012 Seattle, WA","type":"Run","date":"2012-04-14T00:10:33","description":null,"distance_mi":3.21,"moving_time_s":2131,"elevation_m":29.6,"avg_hr":138,"max_hr":169,"avg_cadence":null,"calories":null,"with_pet":null,"with_kid":null},{"id":"128152140","name":"04/14/2012 Seattle, WA","type":"Run","date":"2012-04-14T22:22:33","description":null,"distance_mi":2.82,"moving_time_s":1975,"elevation_m":null,"avg_hr":129,"max_hr":168,"avg_cadence":null,"calories":432,"with_pet":null,"with_kid":null},{"id":"128152130","name":"04/14/2012 Seattle, WA","type":"Run","date":"2012-04-14T23:42:12","description":null,"distance_mi":1.13,"moving_time_s":1257,"elevation_m":148.3,"avg_hr":136,"max_hr":164,"avg_cadence":null,"calories":254,"with_pet":null,"with_kid":null},{"id":"128152121","name":"04/14/2012 Seattle, WA","type":"Run","date":"2012-04-15T00:10:27","description":null,"distance_mi":0.52,"moving_time_s":458,"elevation_m":null,"avg_hr":111,"max_hr":155,"avg_cadence":null,"calories":null,"with_pet":null,"with_kid":null},{"id":"128152116","name":"04/14/2012 Seattle, WA","type":"Run","date":"2012-04-15T00:18:28","description":null,"distance_mi":0.5,"moving_time_s":237,"elevation_m":10.5,"avg_hr":161,"max_hr":177,"avg_cadence":null,"calories":81,"with_pet":null,"with_kid":null},{"id":"128152134","name":"04/15/2012 North Bend, WA","type":"Run","date":"2012-04-15T15:09:52","description":null,"distance_mi":6.44,"moving_time_s":6748,"elevation_m":885.2,"avg_hr":141,"max_hr":166,"avg_cadence":null,"calories":null,"with_pet":null,"with_kid":null}]},{"week":"2012-W16","count":2,"run_count":2,"distance_mi":5.37,"run_distance_mi":5.37,"elevation_m":62.7,"activities":[{"id":"128152101","name":"04/17/2012 Seattle, WA","type":"Run","date":"2012-04-17T14:10:47","description":null,"distance_mi":2.38,"moving_time_s":1550,"elevation_m":62.7,"avg_hr":138,"max_hr":166,"avg_cadence":null,"calories":371,"with_pet":null,"with_kid":null},{"id":"128152092","name":"04/18/2012 Seattle, WA","type":"Run","date":"2012-04-19T01:00:19","description":null,"distance_mi":2.99,"moving_time_s":1708,"elevation_m":null,"avg_hr":null,"max_hr":null,"avg_cadence":null,"calories":455,"with_pet":null,"with_kid":null}]},{"week":"2012-W17","count":3,"run_count":3,"distance_mi":15.27,"run_distance_mi":15.27,"elevation_m":1180.3,"activities":[{"id":"128152086","name":"04/25/2012 Seattle, WA","type":"Run","date":"2012-04-26T02:25:09","description":null,"distance_mi":3.52,"moving_time_s":1823,"elevation_m":71.3,"avg_hr":null,"max_hr":null,"avg_cadence":null,"calories":null,"with_pet":null,"with_kid":null},{"id":"128152085","name":"04/28/2012 Seattle, WA","type":"Run","date":"2012-04-28T23:34:55","description":null,"distance_mi":5.02,"moving_time_s":2678,"elevation_m":134.8,"avg_hr":null,"max_hr":null,"avg_cadence":null,"calories":810,"with_pet":null,"with_kid":null},{"id":"128152100","name":"Mt Si Trail","type":"Run","date":"2012-04-29T15:29:10","description":null,"distance_mi":6.73,"moving_time_s":8353,"elevation_m":974.2,"avg_hr":null,"max_hr":null,"avg_cadence":null,"calories":1524,"with_pet":null,"with_kid":null}]}]},{"month":5,"count":18,"run_count":18,"distance_mi":79.06,"run_distance_mi":79.06,"elevation_m":3421.0,"weeks":[{"week":"2012-W18","count":5,"run_count":5,"distance_mi":20.95,"run_distance_mi":20.95,"elevation_m":1111.6,"activities":[{"id":"128152059","name":"04/30/2012 Bellevue, WA","type":"Run","date":"2012-05-01T00:51:35","description":null,"distance_mi":2.52,"moving_time_s":1288,"elevation_m":70.9,"avg_hr":null,"max_hr":null,"avg_cadence":null,"calories":null,"with_pet":null,"with_kid":null},{"id":"128152051","name":"05/02/2012 Seattle, WA","type":"Run","date":"2012-05-02T13:45:56","description":null,"distance_mi":2.39,"moving_time_s":1180,"elevation_m":35.8,"avg_hr":null,"max_hr":null,"avg_cadence":null,"calories":null,"with_pet":null,"with_kid":null},{"id":"128152053","name":"05/04/2012 Seattle, WA","type":"Run","date":"2012-05-04T13:48:43","description":null,"distance_mi":4.01,"moving_time_s":1962,"elevation_m":71.8,"avg_hr":166,"max_hr":181,"avg_cadence":null,"calories":null,"with_pet":null,"with_kid":null},{"id":"128152046","name":"05/05/2012 Seattle, WA","type":"Run","date":"2012-05-05T23:36:51","description":null,"distance_mi":3.05,"moving_time_s":1626,"elevation_m":null,"avg_hr":null,"max_hr":null,"avg_cadence":null,"calories":null,"with_pet":null,"with_kid":null},{"id":"128152058","name":"West Tiger Loop","type":"Run","date":"2012-05-06T14:20:25","description":null,"distance_mi":8.98,"moving_time_s":7939,"elevation_m":933.1,"avg_hr":null,"max_hr":null,"avg_cadence":null,"calories":null,"with_pet":null,"with_kid":null}]},{"week":"2012-W19","count":4,"run_count":4,"distance_mi":21.67,"run_distance_mi":21.67,"elevation_m":605.8,"activities":[{"id":"128152041","name":"05/09/2012 Seattle, WA","type":"Run","date":"2012-05-10T01:49:21","description":null,"distance_mi":5.15,"moving_time_s":2737,"elevation_m":170.8,"avg_hr":null,"max_hr":null,"avg_cadence":null,"calories":null,"with_pet":null,"with_kid":null},{"id":"128152030","name":"05/10/2012 Seattle, WA","type":"Run","date":"2012-05-11T00:13:09","description":null,"distance_mi":5.04,"moving_time_s":2650,"elevation_m":161.1,"avg_hr":null,"max_hr":null,"avg_cadence":null,"calories":799,"with_pet":null,"with_kid":null},{"id":"128152025","name":"05/12/2012 Seattle, WA","type":"Run","date":"2012-05-12T14:01:14","description":null,"distance_mi":6.43,"moving_time_s":3450,"elevation_m":142.9,"avg_hr":null,"max_hr":null,"avg_cadence":null,"calories":1003,"with_pet":null,"with_kid":null},{"id":"128152018","name":"05/13/2012 Seattle, WA","type":"Run","date":"2012-05-13T14:11:58","description":null,"distance_mi":5.05,"moving_time_s":2702,"elevation_m":131.0,"avg_hr":null,"max_hr":null,"avg_cadence":null,"calories":null,"with_pet":null,"with_kid":null}]},{"week":"2012-W20","count":2,"run_count":2,"distance_mi":7.73,"run_distance_mi":7.73,"elevation_m":602.6,"activities":[{"id":"128152012","name":"05/18/2012 Cape May, NJ","type":"Run","date":"2012-05-18T12:05:37","description":null,"distance_mi":3.23,"moving_time_s":2495,"elevation_m":null,"avg_hr":null,"max_hr":null,"avg_cadence":null,"calories":495,"with_pet":null,"with_kid":null},{"id":"128152007","name":"05/20/2012 Issaquah, WA","type":"Run","date":"2012-05-20T16:17:16","description":null,"distance_mi":4.5,"moving_time_s":4402,"elevation_m":602.6,"avg_hr":null,"max_hr":null,"avg_cadence":null,"calories":null,"with_pet":null,"with_kid":null}]},{"week":"2012-W21","count":4,"run_count":4,"distance_mi":17.82,"run_distance_mi":17.82,"elevation_m":411.2,"activities":[{"id":"128152002","name":"05/23/2012 Seattle, WA","type":"Run","date":"2012-05-24T01:01:11","description":null,"distance_mi":2.38,"moving_time_s":1386,"elevation_m":96.1,"avg_hr":null,"max_hr":null,"avg_cadence":null,"calories":null,"with_pet":null,"with_kid":null},{"id":"128151982","name":"05/24/2012 Seattle, WA","type":"Run","date":"2012-05-24T13:49:44","description":null,"distance_mi":4.03,"moving_time_s":2002,"elevation_m":70.8,"avg_hr":null,"max_hr":null,"avg_cadence":null,"calories":null,"with_pet":null,"with_kid":null},{"id":"128151977","name":"05/26/2012 Seattle, WA","type":"Run","date":"2012-05-26T13:53:56","description":null,"distance_mi":6.59,"moving_time_s":3591,"elevation_m":168.3,"avg_hr":null,"max_hr":null,"avg_cadence":null,"calories":null,"with_pet":null,"with_kid":null},{"id":"128151964","name":"05/27/2012 Seattle, WA","type":"Run","date":"2012-05-27T17:01:15","description":null,"distance_mi":4.82,"moving_time_s":2598,"elevation_m":76.0,"avg_hr":null,"max_hr":null,"avg_cadence":null,"calories":752,"with_pet":null,"with_kid":null}]},{"week":"2012-W22","count":3,"run_count":3,"distance_mi":10.89,"run_distance_mi":10.89,"elevation_m":689.8,"activities":[{"id":"128151975","name":"05/28/2012 Seattle, WA","type":"Run","date":"2012-05-28T14:27:52","description":null,"distance_mi":3.07,"moving_time_s":4019,"elevation_m":480.8,"avg_hr":null,"max_hr":null,"avg_cadence":null,"calories":716,"with_pet":null,"with_kid":null},{"id":"128151950","name":"05/30/2012 Seattle, WA","type":"Run","date":"2012-05-30T13:33:28","description":null,"distance_mi":3.77,"moving_time_s":1969,"elevation_m":76.2,"avg_hr":null,"max_hr":null,"avg_cadence":null,"calories":589,"with_pet":null,"with_kid":null},{"id":"128151948","name":"05/31/2012 Seattle, WA","type":"Run","date":"2012-05-31T13:21:03","description":null,"distance_mi":4.05,"moving_time_s":2127,"elevation_m":132.8,"avg_hr":null,"max_hr":null,"avg_cadence":null,"calories":641,"with_pet":null,"with_kid":null}]}]},{"month":6,"count":20,"run_count":20,"distance_mi":91.06,"run_distance_mi":91.06,"elevation_m":3265.1,"weeks":[{"week":"2012-W22","count":3,"run_count":3,"distance_mi":22.37,"run_distance_mi":22.37,"elevation_m":1562.3,"activities":[{"id":"128151951","name":"06/01/2012 Seattle, WA","type":"Run","date":"2012-06-01T13:11:17","description":null,"distance_mi":4.0,"moving_time_s":2439,"elevation_m":128.8,"avg_hr":null,"max_hr":null,"avg_cadence":null,"calories":null,"with_pet":null,"with_kid":null},{"id":"128151940","name":"06/02/2012 Seattle, WA","type":"Run","date":"2012-06-02T19:01:37","description":null,"distance_mi":2.44,"moving_time_s":1541,"elevation_m":null,"avg_hr":null,"max_hr":null,"avg_cadence":null,"calories":374,"with_pet":null,"with_kid":null},{"id":"128151954","name":"5 Tigers","type":"Run","date":"2012-06-03T14:24:05","description":"West Tiger 3,2,1, Middle Tiger, East Tiger. Not sure I need to do that again!","distance_mi":15.93,"moving_time_s":16200,"elevation_m":1433.5,"avg_hr":null,"max_hr":null,"avg_cadence":null,"calories":3103,"with_pet":null,"with_kid":null}]},{"week":"2012-W23","count":3,"run_count":3,"distance_mi":11.29,"run_distance_mi":11.29,"elevation_m":309.7,"activities":[{"id":"128151918","name":"06/08/2012 Seattle, WA","type":"Run","date":"2012-06-08T15:18:25","description":null,"distance_mi":3.28,"moving_time_s":1658,"elevation_m":28.5,"avg_hr":null,"max_hr":null,"avg_cadence":null,"calories":null,"with_pet":null,"with_kid":null},{"id":"128151911","name":"06/09/2012 Seattle, WA","type":"Run","date":"2012-06-09T14:29:19","description":null,"distance_mi":4.05,"moving_time_s":2110,"elevation_m":132.3,"avg_hr":null,"max_hr":null,"avg_cadence":null,"calories":null,"with_pet":null,"with_kid":null},{"id":"128151903","name":"06/10/2012 Seattle, WA","type":"Run","date":"2012-06-10T14:41:03","description":null,"distance_mi":3.96,"moving_time_s":2502,"elevation_m":148.9,"avg_hr":null,"max_hr":null,"avg_cadence":null,"calories":null,"with_pet":null,"with_kid":null}]},{"week":"2012-W24","count":6,"run_count":6,"distance_mi":24.0,"run_distance_mi":24.0,"elevation_m":665.0,"activities":[{"id":"128151895","name":"06/11/2012 Seattle, WA","type":"Run","date":"2012-06-11T14:05:23","description":null,"distance_mi":2.36,"moving_time_s":1742,"elevation_m":null,"avg_hr":null,"max_hr":null,"avg_cadence":null,"calories":361,"with_pet":null,"with_kid":null},{"id":"128151889","name":"06/12/2012 Seattle, WA","type":"Run","date":"2012-06-12T13:44:23","description":null,"distance_mi":4.04,"moving_time_s":2142,"elevation_m":133.9,"avg_hr":null,"max_hr":null,"avg_cadence":null,"calories":null,"with_pet":null,"with_kid":null},{"id":"128151878","name":"06/13/2012 Seattle, WA","type":"Run","date":"2012-06-13T13:05:33","description":null,"distance_mi":4.05,"moving_time_s":2097,"elevation_m":132.3,"avg_hr":null,"max_hr":null,"avg_cadence":null,"calories":null,"with_pet":null,"with_kid":null},{"id":"128151869","name":"06/14/2012 Seattle, WA","type":"Run","date":"2012-06-14T14:15:44","description":null,"distance_mi":4.34,"moving_time_s":2285,"elevation_m":133.9,"avg_hr":null,"max_hr":null,"avg_cadence":null,"calories":null,"with_pet":null,"with_kid":null},{"id":"128151861","name":"06/15/2012 Seattle, WA","type":"Run","date":"2012-06-15T14:08:42","description":null,"distance_mi":4.82,"moving_time_s":2566,"elevation_m":130.1,"avg_hr":null,"max_hr":null,"avg_cadence":null,"calories":755,"with_pet":null,"with_kid":null},{"id":"128151857","name":"06/17/2012 Seattle, WA","type":"Run","date":"2012-06-17T15:10:38","description":null,"distance_mi":4.39,"moving_time_s":2251,"elevation_m":134.8,"avg_hr":null,"max_hr":null,"avg_cadence":null,"calories":null,"with_pet":null,"with_kid":null}]},{"week":"2012-W25","count":5,"run_count":5,"distance_mi":19.61,"run_distance_mi":19.61,"elevation_m":349.7,"activities":[{"id":"128151847","name":"06/18/2012 Seattle, WA","type":"Run","date":"2012-06-18T14:16:49","description":null,"distance_mi":4.03,"moving_time_s":1976,"elevation_m":70.4,"avg_hr":null,"max_hr":null,"avg_cadence":null,"calories":null,"with_pet":null,"with_kid":null},{"id":"128151840","name":"06/20/2012 Seattle, WA","type":"Run","date":"2012-06-20T13:40:45","description":null,"distance_mi":2.52,"moving_time_s":1544,"elevation_m":null,"avg_hr":null,"max_hr":null,"avg_cadence":null,"calories":383,"with_pet":null,"with_kid":null},{"id":"128151832","name":"Two Phinneys Clockwise NO PAUSE","type":"Run","date":"2012-06-23T13:56:33","description":null,"distance_mi":4.4,"moving_time_s":2248,"elevation_m":129.2,"avg_hr":null,"max_hr":null,"avg_cadence":null,"calories":715,"with_pet":null,"with_kid":null},{"id":"128151828","name":"06/23/2012 Seattle, WA","type":"Run","date":"2012-06-23T15:24:32","description":null,"distance_mi":3.01,"moving_time_s":2008,"elevation_m":null,"avg_hr":null,"max_hr":null,"avg_cadence":null,"calories":459,"with_pet":null,"with_kid":null},{"id":"128151817","name":"06/24/2012 Seattle, WA","type":"Run","date":"2012-06-24T15:22:42","description":null,"distance_mi":5.65,"moving_time_s":2867,"elevation_m":150.1,"avg_hr":null,"max_hr":null,"avg_cadence":null,"calories":null,"with_pet":null,"with_kid":null}]},{"week":"2012-W26","count":3,"run_count":3,"distance_mi":13.79,"run_distance_mi":13.79,"elevation_m":378.4,"activities":[{"id":"128151821","name":"06/26/2012 Seattle, WA","type":"Run","date":"2012-06-26T14:41:40","description":null,"distance_mi":4.03,"moving_time_s":1946,"elevation_m":70.6,"avg_hr":null,"max_hr":null,"avg_cadence":null,"calories":null,"with_pet":null,"with_kid":null},{"id":"128151803","name":"06/28/2012 Seattle, WA","type":"Run","date":"2012-06-28T13:44:49","description":null,"distance_mi":5.72,"moving_time_s":2922,"elevation_m":154.7,"avg_hr":null,"max_hr":null,"avg_cadence":null,"calories":null,"with_pet":null,"with_kid":null},{"id":"128151789","name":"06/29/2012 Seattle, WA","type":"Run","date":"2012-06-29T13:47:24","description":null,"distance_mi":4.04,"moving_time_s":2153,"elevation_m":153.1,"avg_hr":null,"max_hr":null,"avg_cadence":null,"calories":null,"with_pet":null,"with_kid":null}]}]},{"month":7,"count":19,"run_count":19,"distance_mi":88.17,"run_distance_mi":88.17,"elevation_m":4697.5,"weeks":[{"week":"2012-W26","count":1,"run_count":1,"distance_mi":6.93,"run_distance_mi":6.93,"elevation_m":300.9,"activities":[{"id":"128151799","name":"07/01/2012 Ashland, OR","type":"Run","date":"2012-07-01T14:20:01","description":null,"distance_mi":6.93,"moving_time_s":4536,"elevation_m":300.9,"avg_hr":null,"max_hr":null,"avg_cadence":null,"calories":null,"with_pet":null,"with_kid":null}]},{"week":"2012-W27","count":4,"run_count":4,"distance_mi":20.51,"run_distance_mi":20.51,"elevation_m":1408.5,"activities":[{"id":"128151772","name":"07/02/2012 United States, OR","type":"Run","date":"2012-07-02T20:58:10","description":null,"distance_mi":2.04,"moving_time_s":3900,"elevation_m":267.0,"avg_hr":null,"max_hr":null,"avg_cadence":null,"calories":441,"with_pet":null,"with_kid":null},{"id":"128151757","name":"07/03/2012 Sun Valley, ID","type":"Run","date":"2012-07-03T23:54:56","description":null,"distance_mi":4.31,"moving_time_s":2679,"elevation_m":63.3,"avg_hr":null,"max_hr":null,"avg_cadence":null,"calories":null,"with_pet":null,"with_kid":null},{"id":"128151797","name":"07/05/2012 Hailey, ID","type":"Run","date":"2012-07-05T19:39:08","description":null,"distance_mi":6.62,"moving_time_s":8874,"elevation_m":692.8,"avg_hr":null,"max_hr":null,"avg_cadence":null,"calories":1238,"with_pet":null,"with_kid":null},{"id":"128151752","name":"07/06/2012 Lowman, ID","type":"Run","date":"2012-07-06T17:44:37","description":null,"distance_mi":7.54,"moving_time_s":9582,"elevation_m":385.4,"avg_hr":null,"max_hr":null,"avg_cadence":null,"calories":1266,"with_pet":null,"with_kid":null}]},{"week":"2012-W28","count":2,"run_count":2,"distance_mi":6.65,"run_distance_mi":6.65,"elevation_m":192.6,"activities":[{"id":"128151728","name":"07/08/2012 Seattle, WA","type":"Run","date":"2012-07-09T04:00:14","description":null,"distance_mi":4.31,"moving_time_s":2288,"elevation_m":137.1,"avg_hr":null,"max_hr":null,"avg_cadence":null,"calories":678,"with_pet":null,"with_kid":null},{"id":"128151721","name":"07/10/2012 Seattle, WA","type":"Run","date":"2012-07-10T14:37:38","description":null,"distance_mi":2.34,"moving_time_s":1152,"elevation_m":55.5,"avg_hr":null,"max_hr":null,"avg_cadence":null,"calories":362,"with_pet":null,"with_kid":null}]},{"week":"2012-W29","count":5,"run_count":5,"distance_mi":25.15,"run_distance_mi":25.15,"elevation_m":1501.6,"activities":[{"id":"128151718","name":"07/16/2012 Seattle, WA","type":"Run","date":"2012-07-16T14:22:25","description":null,"distance_mi":3.25,"moving_time_s":1627,"elevation_m":80.1,"avg_hr":null,"max_hr":null,"avg_cadence":null,"calories":null,"with_pet":null,"with_kid":null},{"id":"128151709","name":"07/17/2012 Seattle, WA","type":"Run","date":"2012-07-17T14:11:27","description":null,"distance_mi":4.36,"moving_time_s":2250,"elevation_m":128.9,"avg_hr":null,"max_hr":null,"avg_cadence":null,"calories":null,"with_pet":null,"with_kid":null},{"id":"128151711","name":"07/18/2012 Seattle, WA","type":"Run","date":"2012-07-18T14:01:31","description":null,"distance_mi":3.71,"moving_time_s":2001,"elevation_m":164.2,"avg_hr":null,"max_hr":null,"avg_cadence":null,"calories":595,"with_pet":null,"with_kid":null},{"id":"128151700","name":"07/20/2012 Seattle, WA","type":"Run","date":"2012-07-20T13:24:55","description":null,"distance_mi":4.4,"moving_time_s":2287,"elevation_m":154.5,"avg_hr":null,"max_hr":null,"avg_cadence":null,"calories":695,"with_pet":null,"with_kid":null},{"id":"128151717","name":"Mt Si Tenerife Road Lollipop","type":"Run","date":"2012-07-21T18:37:15","description":null,"distance_mi":9.43,"moving_time_s":8699,"elevation_m":973.9,"avg_hr":null,"max_hr":null,"avg_cadence":null,"calories":1898,"with_pet":null,"with_kid":null}]},{"week":"2012-W30","count":5,"run_count":5,"distance_mi":20.3,"run_distance_mi":20.3,"elevation_m":1002.5,"activities":[{"id":"128151697","name":"07/23/2012 Seattle, WA","type":"Run","date":"2012-07-23T14:31:06","description":null,"distance_mi":3.27,"moving_time_s":1701,"elevation_m":71.5,"avg_hr":null,"max_hr":null,"avg_cadence":null,"calories":508,"with_pet":null,"with_kid":null},{"id":"128151681","name":"07/25/2012 Seattle, WA","type":"Run","date":"2012-07-25T13:06:56","description":null,"distance_mi":5.47,"moving_time_s":2869,"elevation_m":175.1,"avg_hr":null,"max_hr":null,"avg_cadence":null,"calories":864,"with_pet":null,"with_kid":null},{"id":"128151670","name":"07/26/2012 Seattle, WA","type":"Run","date":"2012-07-26T14:26:26","description":null,"distance_mi":2.08,"moving_time_s":984,"elevation_m":33.2,"avg_hr":null,"max_hr":null,"avg_cadence":null,"calories":319,"with_pet":null,"with_kid":null},{"id":"128151677","name":"07/28/2012 Winthrop, WA","type":"Run","date":"2012-07-28T18:09:13","description":null,"distance_mi":4.99,"moving_time_s":6711,"elevation_m":555.2,"avg_hr":null,"max_hr":null,"avg_cadence":null,"calories":null,"with_pet":null,"with_kid":null},{"id":"128151654","name":"07/29/2012 Okanogan County, WA, USA, WA","type":"Run","date":"2012-07-29T14:13:15","description":null,"distance_mi":4.49,"moving_time_s":2511,"elevation_m":167.5,"avg_hr":null,"max_hr":null,"avg_cadence":null,"calories":715,"with_pet":null,"with_kid":null}]},{"week":"2012-W31","count":2,"run_count":2,"distance_mi":8.63,"run_distance_mi":8.63,"elevation_m":291.4,"activities":[{"id":"128151642","name":"07/30/2012 Seattle, WA","type":"Run","date":"2012-07-30T14:09:23","description":null,"distance_mi":4.05,"moving_time_s":2861,"elevation_m":137.1,"avg_hr":null,"max_hr":null,"avg_cadence":null,"calories":null,"with_pet":null,"with_kid":null},{"id":"128151639","name":"07/31/2012 Seattle, WA","type":"Run","date":"2012-07-31T13:41:09","description":null,"distance_mi":4.58,"moving_time_s":2317,"elevation_m":154.3,"avg_hr":null,"max_hr":null,"avg_cadence":null,"calories":722,"with_pet":null,"with_kid":null}]}]},{"month":8,"count":22,"run_count":21,"distance_mi":103.82,"run_distance_mi":98.02,"elevation_m":5030.0,"weeks":[{"week":"2012-W31","count":3,"run_count":3,"distance_mi":21.82,"run_distance_mi":21.82,"elevation_m":1212.4,"activities":[{"id":"128151635","name":"08/01/2012 Seattle, WA","type":"Run","date":"2012-08-01T13:10:21","description":null,"distance_mi":4.97,"moving_time_s":2714,"elevation_m":176.9,"avg_hr":null,"max_hr":null,"avg_cadence":null,"calories":797,"with_pet":null,"with_kid":null},{"id":"128151619","name":"08/04/2012 Seattle, WA","type":"Run","date":"2012-08-04T13:44:38","description":null,"distance_mi":6.86,"moving_time_s":3695,"elevation_m":234.2,"avg_hr":null,"max_hr":null,"avg_cadence":null,"calories":null,"with_pet":null,"with_kid":null},{"id":"128151641","name":"Tiger Mountain Loop","type":"Run","date":"2012-08-05T14:24:29","description":null,"distance_mi":9.99,"moving_time_s":8611,"elevation_m":801.3,"avg_hr":null,"max_hr":null,"avg_cadence":null,"calories":null,"with_pet":null,"with_kid":null}]},{"week":"2012-W32","count":5,"run_count":4,"distance_mi":21.55,"run_distance_mi":15.75,"elevation_m":1416.1,"activities":[{"id":"128151604","name":"08/07/2012 Seattle, WA","type":"Run","date":"2012-08-07T13:46:18","description":null,"distance_mi":4.07,"moving_time_s":1944,"elevation_m":72.0,"avg_hr":null,"max_hr":null,"avg_cadence":null,"calories":628,"with_pet":null,"with_kid":null},{"id":"128151595","name":"08/08/2012 Seattle, WA","type":"Run","date":"2012-08-08T14:03:56","description":null,"distance_mi":2.66,"moving_time_s":1935,"elevation_m":94.0,"avg_hr":null,"max_hr":null,"avg_cadence":null,"calories":425,"with_pet":null,"with_kid":null},{"id":"128151593","name":"08/09/2012 Seattle, WA","type":"Run","date":"2012-08-09T13:51:51","description":null,"distance_mi":4.31,"moving_time_s":2271,"elevation_m":159.8,"avg_hr":null,"max_hr":null,"avg_cadence":null,"calories":null,"with_pet":null,"with_kid":null},{"id":"128151612","name":"Not Mt Eleanor","type":"Hike","date":"2012-08-11T19:27:53","description":"We were prevented from going to Mt Eleanor by a marauding mountain goat. Fine = $1000 to set foot on the trail!","distance_mi":5.8,"moving_time_s":10902,"elevation_m":1090.3,"avg_hr":null,"max_hr":null,"avg_cadence":null,"calories":null,"with_pet":null,"with_kid":null},{"id":"128151585","name":"08/12/2012 Brinnon, WA","type":"Run","date":"2012-08-12T17:56:56","description":null,"distance_mi":4.71,"moving_time_s":4750,"elevation_m":null,"avg_hr":null,"max_hr":null,"avg_cadence":null,"calories":718,"with_pet":null,"with_kid":null}]},{"week":"2012-W33","count":5,"run_count":5,"distance_mi":21.21,"run_distance_mi":21.21,"elevation_m":1120.8,"activities":[{"id":"128151504","name":"08/13/2012 Seattle, WA","type":"Run","date":"2012-08-13T13:57:11","description":null,"distance_mi":4.39,"moving_time_s":2202,"elevation_m":134.9,"avg_hr":null,"max_hr":null,"avg_cadence":null,"calories":690,"with_pet":null,"with_kid":null},{"id":"128151516","name":"08/15/2012 Seattle, WA","type":"Run","date":"2012-08-15T14:05:01","description":null,"distance_mi":4.41,"moving_time_s":2263,"elevation_m":134.1,"avg_hr":null,"max_hr":null,"avg_cadence":null,"calories":703,"with_pet":null,"with_kid":null},{"id":"128151511","name":"08/16/2012 Seattle, WA","type":"Run","date":"2012-08-16T14:08:33","description":null,"distance_mi":2.48,"moving_time_s":1782,"elevation_m":18.5,"avg_hr":null,"max_hr":null,"avg_cadence":null,"calories":null,"with_pet":null,"with_kid":null},{"id":"128151536","name":"08/18/2012 Issaquah, WA","type":"Run","date":"2012-08-18T17:24:10","description":null,"distance_mi":7.9,"moving_time_s":7260,"elevation_m":833.3,"avg_hr":null,"max_hr":null,"avg_cadence":null,"calories":1590,"with_pet":null,"with_kid":null},{"id":"128151482","name":"08/19/2012 Seattle, WA","type":"Run","date":"2012-08-19T19:59:20","description":null,"distance_mi":2.03,"moving_time_s":1916,"elevation_m":null,"avg_hr":null,"max_hr":null,"avg_cadence":null,"calories":null,"with_pet":null,"with_kid":null}]},{"week":"2012-W34","count":5,"run_count":5,"distance_mi":22.65,"run_distance_mi":22.65,"elevation_m":862.0,"activities":[{"id":"128151479","name":"08/20/2012 Seattle, WA","type":"Run","date":"2012-08-20T14:05:19","description":null,"distance_mi":4.39,"moving_time_s":2223,"elevation_m":135.6,"avg_hr":null,"max_hr":null,"avg_cadence":null,"calories":null,"with_pet":null,"with_kid":null},{"id":"128151470","name":"08/21/2012 Seattle, WA","type":"Run","date":"2012-08-21T13:42:03","description":null,"distance_mi":4.34,"moving_time_s":2250,"elevation_m":160.9,"avg_hr":null,"max_hr":null,"avg_cadence":null,"calories":700,"with_pet":null,"with_kid":null},{"id":"128151455","name":"08/23/2012 Seattle, WA","type":"Run","date":"2012-08-23T13:55:20","description":null,"distance_mi":4.26,"moving_time_s":2212,"elevation_m":155.5,"avg_hr":null,"max_hr":null,"avg_cadence":null,"calories":684,"with_pet":null,"with_kid":null},{"id":"128151475","name":"08/24/2012 Newcastle, WA","type":"Run","date":"2012-08-25T00:38:43","description":null,"distance_mi":5.31,"moving_time_s":3599,"elevation_m":248.1,"avg_hr":null,"max_hr":null,"avg_cadence":null,"calories":892,"with_pet":null,"with_kid":null},{"id":"128151440","name":"08/25/2012 Seattle, WA","type":"Run","date":"2012-08-25T14:50:22","description":null,"distance_mi":4.35,"moving_time_s":2219,"elevation_m":161.9,"avg_hr":null,"max_hr":null,"avg_cadence":null,"calories":702,"with_pet":null,"with_kid":null}]},{"week":"2012-W35","count":4,"run_count":4,"distance_mi":16.59,"run_distance_mi":16.59,"elevation_m":418.7,"activities":[{"id":"128151431","name":"Two Phinneys Clockwise","type":"Run","date":"2012-08-27T14:17:11","description":null,"distance_mi":4.43,"moving_time_s":2268,"elevation_m":130.0,"avg_hr":null,"max_hr":null,"avg_cadence":null,"calories":null,"with_pet":null,"with_kid":null},{"id":"128151421","name":"08/28/2012 Seattle, WA","type":"Run","date":"2012-08-28T14:21:31","description":null,"distance_mi":3.8,"moving_time_s":1885,"elevation_m":73.1,"avg_hr":null,"max_hr":null,"avg_cadence":null,"calories":null,"with_pet":null,"with_kid":null},{"id":"128151406","name":"Tangletown Hilly 4-miler","type":"Run","date":"2012-08-29T14:18:19","description":"Breaking the 8-min/mile pace on this run was amazing. Don't think I'll ever do it again, but who knows?","distance_mi":3.97,"moving_time_s":1891,"elevation_m":68.8,"avg_hr":null,"max_hr":null,"avg_cadence":null,"calories":629,"with_pet":null,"with_kid":null},{"id":"128151402","name":"08/31/2012 Seattle, WA","type":"Run","date":"2012-08-31T13:51:06","description":null,"distance_mi":4.39,"moving_time_s":2174,"elevation_m":146.8,"avg_hr":null,"max_hr":null,"avg_cadence":null,"calories":689,"with_pet":null,"with_kid":null}]}]},{"month":9,"count":6,"run_count":5,"distance_mi":26.5,"run_distance_mi":14.79,"elevation_m":1998.8,"weeks":[{"week":"2012-W35","count":2,"run_count":1,"distance_mi":13.92,"run_distance_mi":2.21,"elevation_m":1808.1,"activities":[{"id":"128151395","name":"09/01/2012 Seattle, WA","type":"Run","date":"2012-09-01T14:29:15","description":null,"distance_mi":2.21,"moving_time_s":1187,"elevation_m":51.4,"avg_hr":null,"max_hr":null,"avg_cadence":null,"calories":349,"with_pet":null,"with_kid":null},{"id":"128151414","name":"Sourdough Mountain","type":"Hike","date":"2012-09-02T12:00:43","description":null,"distance_mi":11.71,"moving_time_s":19988,"elevation_m":1756.7,"avg_hr":null,"max_hr":null,"avg_cadence":null,"calories":1838,"with_pet":null,"with_kid":null}]},{"week":"2012-W36","count":2,"run_count":2,"distance_mi":6.09,"run_distance_mi":6.09,"elevation_m":77.5,"activities":[{"id":"128151386","name":"09/05/2012 Seattle, WA","type":"Run","date":"2012-09-05T13:47:32","description":null,"distance_mi":3.3,"moving_time_s":1652,"elevation_m":77.5,"avg_hr":null,"max_hr":null,"avg_cadence":null,"calories":517,"with_pet":null,"with_kid":null},{"id":"128151372","name":"09/07/2012 Seattle, WA","type":"Run","date":"2012-09-07T13:51:08","description":null,"distance_mi":2.79,"moving_time_s":1338,"elevation_m":null,"avg_hr":null,"max_hr":null,"avg_cadence":null,"calories":425,"with_pet":null,"with_kid":null}]},{"week":"2012-W38","count":2,"run_count":2,"distance_mi":6.49,"run_distance_mi":6.49,"elevation_m":113.2,"activities":[{"id":"128151366","name":"09/20/2012 Seattle, WA","type":"Run","date":"2012-09-20T13:39:25","description":null,"distance_mi":2.37,"moving_time_s":2884,"elevation_m":null,"avg_hr":null,"max_hr":null,"avg_cadence":null,"calories":364,"with_pet":null,"with_kid":null},{"id":"128151353","name":"09/22/2012 Seattle, WA","type":"Run","date":"2012-09-22T16:12:43","description":null,"distance_mi":4.12,"moving_time_s":2125,"elevation_m":113.2,"avg_hr":null,"max_hr":null,"avg_cadence":null,"calories":null,"with_pet":null,"with_kid":null}]}]},{"month":11,"count":5,"run_count":5,"distance_mi":29.94,"run_distance_mi":29.94,"elevation_m":1444.9,"weeks":[{"week":"2012-W44","count":1,"run_count":1,"distance_mi":9.67,"run_distance_mi":9.67,"elevation_m":980.3,"activities":[{"id":"128151373","name":"West Tiger Lollipop using railroad grade","type":"Run","date":"2012-11-04T15:20:46","description":null,"distance_mi":9.67,"moving_time_s":7976,"elevation_m":980.3,"avg_hr":null,"max_hr":null,"avg_cadence":null,"calories":1889,"with_pet":null,"with_kid":null}]},{"week":"2012-W45","count":3,"run_count":3,"distance_mi":13.65,"run_distance_mi":13.65,"elevation_m":284.3,"activities":[{"id":"128151324","name":"Green Lake Inner clockwise","type":"Run","date":"2012-11-08T14:52:44","description":null,"distance_mi":2.8,"moving_time_s":1338,"elevation_m":null,"avg_hr":null,"max_hr":null,"avg_cadence":null,"calories":438,"with_pet":null,"with_kid":null},{"id":"128151326","name":"Madison Park Loop with David Midgley","type":"Run","date":"2012-11-10T17:08:05","description":null,"distance_mi":7.77,"moving_time_s":3993,"elevation_m":204.3,"avg_hr":null,"max_hr":null,"avg_cadence":null,"calories":null,"with_pet":null,"with_kid":null},{"id":"128151310","name":"11/11/2012 Seattle, WA","type":"Run","date":"2012-11-11T23:40:36","description":null,"distance_mi":3.08,"moving_time_s":1596,"elevation_m":80.0,"avg_hr":null,"max_hr":null,"avg_cadence":null,"calories":485,"with_pet":null,"with_kid":null}]},{"week":"2012-W46","count":1,"run_count":1,"distance_mi":6.62,"run_distance_mi":6.62,"elevation_m":180.3,"activities":[{"id":"128151315","name":"11/17/2012 Seattle, WA","type":"Run","date":"2012-11-17T17:04:01","description":null,"distance_mi":6.62,"moving_time_s":3474,"elevation_m":180.3,"avg_hr":null,"max_hr":null,"avg_cadence":null,"calories":1046,"with_pet":null,"with_kid":null}]}]},{"month":12,"count":2,"run_count":2,"distance_mi":8.4,"run_distance_mi":8.4,"elevation_m":164.6,"weeks":[{"week":"2012-W49","count":2,"run_count":2,"distance_mi":8.4,"run_distance_mi":8.4,"elevation_m":164.6,"activities":[{"id":"128151294","name":"12/06/2012 Seattle, WA","type":"Run","date":"2012-12-07T02:55:25","description":null,"distance_mi":2.78,"moving_time_s":1377,"elevation_m":null,"avg_hr":null,"max_hr":null,"avg_cadence":null,"calories":424,"with_pet":null,"with_kid":null},{"id":"128151305","name":"12/09/2012 Seattle, WA","type":"Run","date":"2012-12-09T17:39:27","description":null,"distance_mi":5.62,"moving_time_s":3036,"elevation_m":164.6,"avg_hr":null,"max_hr":null,"avg_cadence":null,"calories":890,"with_pet":null,"with_kid":null}]}]}]}