{"month":8,"count":19,"run_count":18,"distance_mi":81.55,"run_distance_mi":63.78,"elevation_m":1549.0,"weeks":[{"week":"2021-W31","count":5,"run_count":5,"distance_mi":14.34,"run_distance_mi":14.34,"elevation_m":304.0,"activities":[{"id":"5726759993","name":"Slow is better than no","type":"Run","date":"2021-08-02T14:33:05","description":null,"distance_mi":3.51,"moving_time_s":1994,"elevation_m":76.0,"avg_hr":null,"max_hr":null,"avg_cadence":80,"calories":453,"with_pet":null,"with_kid":null},{"id":"5743999458","name":"Better than Monday!","type":"Run","date":"2021-08-05T16:14:09","description":null,"distance_mi":2.65,"moving_time_s":1466,"elevation_m":54.0,"avg_hr":null,"max_hr":null,"avg_cadence":80,"calories":344,"with_pet":null,"with_kid":null},{"id":"5749731963","name":"Base miles for the 2040 Geri(atric)-Olympics","type":"Run","date":"2021-08-06T18:57:35","description":"Let\u2019s make it a thing!","distance_mi":3.63,"moving_time_s":2056,"elevation_m":78.0,"avg_hr":null,"max_hr":null,"avg_cadence":79,"calories":486,"with_pet":null,"with_kid":null},{"id":"5754326328","name":"North Cap Hill with Evan, Herve, Ana, and Anita","type":"Run","date":"2021-08-07T15:32:23","description":"Missed the first mile up to and around Volunteer Park","distance_mi":3.55,"moving_time_s":2270,"elevation_m":96.0,"avg_hr":null,"max_hr":null,"avg_cadence":77,"calories":458,"with_pet":null,"with_kid":null},{"id":"5754858286","name":"Missed mile","type":"Run","date":"2021-08-07T15:33:00","description":null,"distance_mi":1.0,"moving_time_s":600,"elevation_m":null,"avg_hr":null,"max_hr":null,"avg_cadence":null,"calories":157,"with_pet":null,"with_kid":null}]},{"week":"2021-W32","count":3,"run_count":3,"distance_mi":9.71,"run_distance_mi":9.71,"elevation_m":189.0,"activities":[{"id":"5769355320","name":"Struggle fest","type":"Run","date":"2021-08-10T12:57:09","description":null,"distance_mi":4.55,"moving_time_s":2716,"elevation_m":73.0,"avg_hr":null,"max_hr":null,"avg_cadence":78,"calories":600,"with_pet":null,"with_kid":null},{"id":"5781033687","name":"Little loop in the morning","type":"Run","date":"2021-08-12T13:33:04","description":"Track isn\u2019t pretty but running less than 2 miles isn\u2019t pretty either","distance_mi":2.13,"moving_time_s":1207,"elevation_m":43.0,"avg_hr":null,"max_hr":null,"avg_cadence":80,"calories":280,"with_pet":null,"with_kid":null},{"id":"5798300172","name":"Slowly getting slower","type":"Run","date":"2021-08-15T16:43:25","description":"So be it.","distance_mi":3.03,"moving_time_s":1861,"elevation_m":73.0,"avg_hr":null,"max_hr":null,"avg_cadence":77,"calories":391,"with_pet":null,"with_kid":null}]},{"week":"2021-W33","count":6,"run_count":5,"distance_mi":37.08,"run_distance_mi":19.31,"elevation_m":689.0,"activities":[{"id":"5802307421","name":"Runs better when cool","type":"Run","date":"2021-08-16T14:34:00","description":"And much better when cold. Bring on the Fall!","distance_mi":3.65,"moving_time_s":2065,"elevation_m":77.0,"avg_hr":null,"max_hr":null,"avg_cadence":80,"calories":479,"with_pet":null,"with_kid":null},{"id":"5807728266","name":"Cooler and cooler","type":"Run","date":"2021-08-17T14:55:49","description":"Ya gotta love 56 degrees\n\n\u2026 unless it\u2019s Celsius of course.","distance_mi":4.01,"moving_time_s":2243,"elevation_m":87.0,"avg_hr":null,"max_hr":null,"avg_cadence":80,"calories":530,"with_pet":null,"with_kid":null},{"id":"5818980653","name":"Back to the horror of \u201csunny and 60\u201d","type":"Run","date":"2021-08-19T15:47:20","description":"Yes\u2026 I am a delicate flower","distance_mi":2.71,"moving_time_s":1506,"elevation_m":52.0,"avg_hr":null,"max_hr":null,"avg_cadence":80,"calories":356,"with_pet":null,"with_kid":null},{"id":"5822113211","name":"Fremont lookout at dusk","type":"Run","date":"2021-08-20T00:23:32","description":"Spending sunset at Sunrise with Chris. Didn\u2019t think we would be inside the clouds","distance_mi":5.92,"moving_time_s":8229,"elevation_m":376.0,"avg_hr":null,"max_hr":null,"avg_cadence":57,"calories":583,"with_pet":null,"with_kid":null},{"id":"5831287161","name":"Palouse to Cascades through the canyon of the Yakima with Chris","type":"Ride","date":"2021-08-21T18:28:41","description":"Soft gravel all the way \u2014 more work than we had bargained for","distance_mi":17.77,"moving_time_s":12137,"elevation_m":62.0,"avg_hr":null,"max_hr":null,"avg_cadence":null,"calories":608,"with_pet":null,"with_kid":null},{"id":"5835753573","name":"Where golf is king","type":"Run","date":"2021-08-22T15:50:39","description":"I wonder what the Roslyn coal miners would think of Suncadia?","distance_mi":3.02,"moving_time_s":1848,"elevation_m":35.0,"avg_hr":null,"max_hr":null,"avg_cadence":79,"calories":385,"with_pet":null,"with_kid":null}]},{"week":"2021-W34","count":4,"run_count":4,"distance_mi":14.19,"run_distance_mi":14.19,"elevation_m":271.0,"activities":[{"id":"5840039331","name":"Need a name for this new short loop","type":"Run","date":"2021-08-23T14:55:10","description":null,"distance_mi":2.67,"moving_time_s":1451,"elevation_m":58.0,"avg_hr":null,"max_hr":null,"avg_cadence":81,"calories":353,"with_pet":null,"with_kid":null},{"id":"5845482989","name":"Building back","type":"Run","date":"2021-08-24T14:17:40","description":"Ask me about \u201cbetter\u201d later","distance_mi":4.17,"moving_time_s":2301,"elevation_m":73.0,"avg_hr":null,"max_hr":null,"avg_cadence":80,"calories":551,"with_pet":null,"with_kid":null},{"id":"5856702444","name":"Combing it again","type":"Run","date":"2021-08-26T14:03:09","description":"A little smoother and a little longer","distance_mi":4.82,"moving_time_s":2804,"elevation_m":99.0,"avg_hr":null,"max_hr":null,"avg_cadence":79,"calories":650,"with_pet":null,"with_kid":null},{"id":"5868126161","name":"Morning Run","type":"Run","date":"2021-08-28T17:10:36","description":null,"distance_mi":2.53,"moving_time_s":1444,"elevation_m":41.0,"avg_hr":null,"max_hr":null,"avg_cadence":80,"calories":333,"with_pet":null,"with_kid":null}]},{"week":"2021-W35","count":1,"run_count":1,"distance_mi":6.23,"run_distance_mi":6.23,"elevation_m":96.0,"activities":[{"id":"5877612113","name":"Nice cool morning on the toast loop","type":"Run","date":"2021-08-30T14:00:13","description":"Still stopped a few times to cool down, but doing better than a month sgo","distance_mi":6.23,"moving_time_s":3529,"elevation_m":96.0,"avg_hr":null,"max_hr":null,"avg_cadence":80,"calories":811,"with_pet":null,"with_kid":null}]}]}